kopl/__init__.py
kopl/data.py
kopl/kopl.py
kopl/util.py
kopl/test/__init__.py
kopl/test/test_example.py
KoPL-0.0.5.dist-info/METADATA
KoPL-0.0.5.dist-info/WHEEL
KoPL-0.0.5.dist-info/top_level.txt
KoPL-0.0.5.dist-info/RECORD
