Metadata-Version: 2.1
Name: KoPL
Version: 0.0.5
Summary: KoPL Executor
Home-page: https://github.com/THU-KEG/KoPL
Author: KEG
Author-email: caosl19@mails.tsinghua.edu.cn
License: UNKNOWN
Project-URL: Bug Tracker, https://github.com/THU-KEG/KoPL/issues
Platform: UNKNOWN
Classifier: Programming Language :: Python :: 3
Classifier: License :: OSI Approved :: GNU General Public License v3 (GPLv3)
Classifier: Operating System :: OS Independent
Requires-Python: >=3.6
